{
  "itemId": "552",
  "name": "钢质瓶",
  "tables": [
    {
      "rows": 6,
      "columns": 3,
      "headers": [
        [
          {
            "type": "text",
            "text": "合成设备"
          }
        ],
        [
          {
            "type": "text",
            "text": "原料需求"
          }
        ],
        [
          {
            "type": "text",
            "text": "合成产物"
          }
        ]
      ],
      "data": [
        [
          [
            {
              "type": "entry",
              "id": "172",
              "count": "0"
            }
          ],
          [
            {
              "type": "entry",
              "id": "555",
              "count": "2"
            }
          ],
          [
            {
              "type": "entry",
              "id": "552",
              "count": "1"
            }
          ]
        ],
        [
          [
            {
              "type": "entry",
              "id": "745",
              "count": "0"
            }
          ],
          [
            {
              "type": "entry",
              "id": "552",
              "count": "1"
            }
          ],
          [
            {
              "type": "entry",
              "id": "552",
              "count": "1"
            },
            {
              "type": "entry",
              "id": "381",
              "count": "1"
            }
          ]
        ],
        [
          [
            {
              "type": "entry",
              "id": "176",
              "count": "0"
            }
          ],
          [
            {
              "type": "entry",
              "id": "552",
              "count": "1"
            },
            {
              "type": "entry",
              "id": "381",
              "count": "1"
            }
          ],
          [
            {
              "type": "entry",
              "id": "552",
              "count": "1"
            }
          ]
        ],
        [
          [],
          [
            {
              "type": "entry",
              "id": "552",
              "count": "10"
            },
            {
              "type": "entry",
              "id": "553",
              "count": "10"
            }
          ],
          [
            {
              "type": "entry",
              "id": "526",
              "count": "1"
            }
          ]
        ],
        [
          [],
          [
            {
              "type": "entry",
              "id": "552",
              "count": "10"
            },
            {
              "type": "entry",
              "id": "554",
              "count": "10"
            }
          ],
          [
            {
              "type": "entry",
              "id": "527",
              "count": "1"
            }
          ]
        ]
      ]
    }
  ]
}